video_editor_mcp/__init__.py
video_editor_mcp/edit.json
video_editor_mcp/generate_charts.py
video_editor_mcp/generate_opentimeline.py
video_editor_mcp/search_local_videos.py
video_editor_mcp/server.py
video_editor_mcp_fastmcp-0.1.60.dist-info/METADATA
video_editor_mcp_fastmcp-0.1.60.dist-info/WHEEL
video_editor_mcp_fastmcp-0.1.60.dist-info/entry_points.txt
video_editor_mcp_fastmcp-0.1.60.dist-info/RECORD
